nina_funcs.py
nina_funcs-1.0.2.dist-info/LICENSE
nina_funcs-1.0.2.dist-info/METADATA
nina_funcs-1.0.2.dist-info/WHEEL
nina_funcs-1.0.2.dist-info/top_level.txt
nina_funcs-1.0.2.dist-info/RECORD
