Metadata-Version: 2.1
Name: nina-funcs
Version: 1.0.2
Summary: Test Package for NINAPRO
Home-page: UNKNOWN
Author: Shreyas P J
License: UNKNOWN
Platform: UNKNOWN
Classifier: Programming Language :: Python :: 3
Classifier: License :: OSI Approved :: MIT License
Classifier: Operating System :: OS Independent
Requires-Python: >=3.6
License-File: LICENSE
